senzo/__init__.py
senzo/generator.py
senzo/operation.py
senzo/parser.py
senzo/settings.py
senzo/type_space.py
senzo/backends/__init__.py
senzo/backends/base.py
senzo/backends/dataclass/__init__.py
senzo/backends/dataclass/msgspec.py
senzo/backends/dataclass/pydantic.py
senzo/backends/http/__init__.py
senzo/backends/http/aiohttp.py
senzo/backends/http/httpx.py
senzo/backends/http/requests.py
senzo/codegen/__init__.py
senzo/codegen/utils.py
senzo-0.1.0.dist-info/METADATA
senzo-0.1.0.dist-info/WHEEL
senzo-0.1.0.dist-info/RECORD
