Metadata-Version: 2.4
Name: senzo
Version: 0.1.0
Summary: Generate typed Python API clients from OpenAPI specs
Requires-Python: >=3.10
Requires-Dist: libcst>=1.8.6
Requires-Dist: openapi-spec-validator>=0.7.2
Requires-Dist: pydantic>=2.12.5
Requires-Dist: pyyaml>=6.0.3
Requires-Dist: typing-extensions>=4.0.0; python_version < '3.11'
